leaflet/__init__.py
leaflet/control.py
leaflet/controller.py
leaflet/samtools.py
leaflet/usersocket.py
leaflet/examples/basic.py
leaflet/examples/datagram.py
leaflet-0.0.3.dist-info/DESCRIPTION.rst
leaflet-0.0.3.dist-info/METADATA
leaflet-0.0.3.dist-info/RECORD
leaflet-0.0.3.dist-info/WHEEL
leaflet-0.0.3.dist-info/metadata.json
leaflet-0.0.3.dist-info/top_level.txt
