Metadata-Version: 1.2
Name: leaflet
Version: 0.0.3
Summary: Dead simple I2P SAM library
Home-page: https://github.com/MuxZeroNet/leaflet
Author: MuxZeroNet
Author-email: muxzeronet@users.noreply.github.com
License: MIT
Keywords: I2P SAM socket
Platform: UNKNOWN
Classifier: Development Status :: 3 - Alpha
Classifier: Intended Audience :: Developers
Classifier: Topic :: Software Development :: Libraries
Classifier: License :: OSI Approved :: MIT License
Classifier: Programming Language :: Python :: 3
Requires-Python: >=3
